tests/__init__.py
tests/fixtures.py
tests/test_contract.py
tests/test_fee_delegation.py
tests/test_integration.py
tests/test_multi.py
tests/test_replay.py
tests/test_ticker.py
tests/test_timeout.py
tests/test_vet.py
tests/test_vtho.py
thor_requests/__init__.py
thor_requests/clause.py
thor_requests/connect.py
thor_requests/const.py
thor_requests/contract.py
thor_requests/file_utils.py
thor_requests/utils.py
thor_requests/wallet.py
thor_requests-1.2.5.dist-info/LICENSE
thor_requests-1.2.5.dist-info/METADATA
thor_requests-1.2.5.dist-info/WHEEL
thor_requests-1.2.5.dist-info/top_level.txt
thor_requests-1.2.5.dist-info/RECORD
