Metadata-Version: 2.1
Name: thor-requests
Version: 1.2.5
Summary: Simple network VeChain SDK for human to interact with the blockchain
Home-page: https://github.com/laalaguer/thor-requests
Author: laalaguer
Author-email: laalaguer@gmail.com
License: UNKNOWN
Project-URL: Documentation, https://github.com/laalaguer/thor-requests
Project-URL: Source, https://github.com/laalaguer/thor-requests
Project-URL: Issue Tracker, https://github.com/laalaguer/thor-requests/issues
Keywords: vechain thor blockchain sdk requests
Platform: UNKNOWN
Classifier: Programming Language :: Python :: 3
Classifier: Intended Audience :: Developers
Classifier: Topic :: Software Development :: Build Tools
Classifier: License :: OSI Approved :: GNU General Public License v3 (GPLv3)
Classifier: Operating System :: OS Independent
Requires-Python: >=3.6
License-File: LICENSE
Requires-Dist: wheel
Requires-Dist: twine
Requires-Dist: requests
Requires-Dist: thor-devkit (==1.0.14)
Requires-Dist: pytest
Requires-Dist: pytest-cov
